Flora/__init__.py
Flora/main.py
Flora/commands/Core.py
Flora/commands/Moderator.py
Flora/commands/__init__.py
Flora/commands/fun.py
Flora/commands/greet.py
Flora/utils/__init__.py
Flora/utils/checks.py
Flora/utils/color_print.py
Flora/utils/config.py
Flora/utils/errors.py
Flora/utils/psuedo_db.py
Flora/utils/setupstuff.py
Flora/utils/utils.py
Flora/utils/values.py
Flora/utils/config/config.yml
Flora/utils/config/Plugins/__init__.py
Flora/utils/config/Plugins/Plugin/__init__.py
Flora-0.0.1a1.dist-info/DESCRIPTION.rst
Flora-0.0.1a1.dist-info/METADATA
Flora-0.0.1a1.dist-info/RECORD
Flora-0.0.1a1.dist-info/WHEEL
Flora-0.0.1a1.dist-info/entry_points.txt
Flora-0.0.1a1.dist-info/metadata.json
Flora-0.0.1a1.dist-info/top_level.txt
