Metadata-Version: 2.0
Name: Flora
Version: 0.0.1a1
Summary: Flora
Home-page: https://fuzen-py.github.io/Flora/
Author: UNKNOWN
Author-email: UNKNOWN
License: MIT
Platform: UNKNOWN
Classifier: Development Status :: 3 - Alpha
Classifier: License :: OSI Approved :: MIT License
Classifier: Programming Language :: Python :: 3.6
Classifier: Programming Language :: Python :: 3 :: Only
Requires-Dist: discord.py
Requires-Dist: pyYaml
Requires-Dist: ujson
